aiokcp/__init__.py
aiokcp/core.py
aiokcp/crypto.py
aiokcp/exceptions.py
aiokcp/ikcp.c
aiokcp/ikcp.h
aiokcp/kcp.c
aiokcp/kcp.cp310-win_amd64.pyd
aiokcp/kcp.pyi
aiokcp/stream.py
aiokcp/utils.py
aiokcp/sync/__init__.py
aiokcp/sync/server.py
aiokcp/sync/sock.py
aiokcp-0.0.4.dist-info/LICENSE
aiokcp-0.0.4.dist-info/METADATA
aiokcp-0.0.4.dist-info/WHEEL
aiokcp-0.0.4.dist-info/top_level.txt
aiokcp-0.0.4.dist-info/RECORD
