Metadata-Version: 2.1
Name: aiokcp
Version: 0.0.4
Summary: KCP for asyncio and socketserver, based on kcp
Author: ryanrain2016
Author-email: ryanrain2016 <holidaylover2010@gmail.com>
Project-URL: Homepage, https://github.com/ryanrain2016/aiokcp
Project-URL: Issues, https://github.com/ryanrain2016/aiokcp/issues
Keywords: asyncio,kcp,socket,aio,aiokcp
Classifier: Programming Language :: Python :: 3
Classifier: Intended Audience :: Developers
Classifier: License :: OSI Approved :: MIT License
Classifier: Operating System :: OS Independent
Requires-Python: >=3.8
License-File: LICENSE
Requires-Dist: cython
Provides-Extra: crypto
Requires-Dist: cryptography ; extra == 'crypto'
